easy_exon/__init__.py
easy_exon/client.py
easy_exon/exceptions.py
easy_exon/filters/__init__.py
easy_exon/filters/builder.py
easy_exon/filters/enums.py
easy_exon/models/__init__.py
easy_exon/models/object.py
easy_exon/models/organization.py
easy_exon/models/user.py
easy_exon/models/act/certificate.py
easy_exon/models/act/estimate.py
easy_exon/models/isr/csg.py
easy_exon/models/isr/work.py
easy_exon/models/itd/act.py
easy_exon/models/itd/common.py
easy_exon/models/itd/general_journal.py
easy_exon/models/itd/material.py
easy_exon/models/itd/ojr.py
easy_exon/models/itd/order.py
easy_exon/models/itd/schema.py
easy_exon/models/itd/task.py
easy_exon/models/otitb/act.py
easy_exon/models/otitb/document.py
easy_exon/models/otitb/journal.py
easy_exon/models/pir/expertise.py
easy_exon/models/pir/project_work_doc.py
easy_exon/models/pir/vpr_doc.py
easy_exon/models/pir/work_doc.py
easy_exon/models/pir/work_extra.py
easy_exon/models/sk/common.py
easy_exon/models/sk/document.py
easy_exon/models/sk/inspection.py
easy_exon/models/sk/journal.py
easy_exon/models/sk/registry.py
easy_exon/models/sk/remark.py
easy_exon/resources/__init__.py
easy_exon/resources/objects.py
easy_exon/resources/organizations.py
easy_exon/resources/users.py
easy_exon/resources/act/certificates.py
easy_exon/resources/act/estimates.py
easy_exon/resources/isr/csgs.py
easy_exon/resources/isr/works.py
easy_exon/resources/itd/acts.py
easy_exon/resources/itd/general_journals.py
easy_exon/resources/itd/materials.py
easy_exon/resources/itd/ojrs.py
easy_exon/resources/itd/orders.py
easy_exon/resources/itd/schemas.py
easy_exon/resources/itd/tasks.py
easy_exon/resources/otitb/acts.py
easy_exon/resources/otitb/documents.py
easy_exon/resources/otitb/journals.py
easy_exon/resources/pir/expertises.py
easy_exon/resources/pir/project_work_docs.py
easy_exon/resources/pir/vpr_docs.py
easy_exon/resources/pir/work_docs.py
easy_exon/resources/pir/work_extras.py
easy_exon/resources/sk/documents.py
easy_exon-0.0.9.dist-info/METADATA
easy_exon-0.0.9.dist-info/WHEEL
easy_exon-0.0.9.dist-info/licenses/LICENSE
easy_exon-0.0.9.dist-info/RECORD
