Metadata-Version: 2.4
Name: easy-exon
Version: 0.0.9
Summary: Exon API wrapper
Project-URL: Homepage, https://github.com/fallec/easy-exon
Project-URL: Documentation, https://github.com/fallec/easy-exon
Author-email: Andrew <falla.code@gmail.com>, Kirill <newmetarllyop@gmail.com>
License: MIT License
License-File: LICENSE
Requires-Dist: pydantic>=2.11.7
